[
  {"id":"FR1","name":"Pixie Dust Fertilizer","faction":"Fairy","tier":1,"cost":"5e7","effect":"Increase the base production of Farms by +98. Reduces cost multiplier by 0.02 (becomes 1.13).","formula":"","effects":["Specific Buildings","Building Cost Reduction"],"scaling":[],"window":[]},
  {"id":"FR2","name":"Fairy Workers","faction":"Fairy","tier":1,"cost":"5e8","effect":"Increase the production of Farms, Inns and Blacksmiths by 10,000%.","formula":"","effects":["Specific Buildings"],"scaling":[],"window":[]},
  {"id":"FR3","name":"Kind Hearts","faction":"Fairy","tier":1,"cost":"5e9","effect":"Increases maximum Mana additively based on Good buildings owned.","formula":"+(1.3 * x ^ 0.7), where x is Good buildings owned","effects":["Mana & Spells"],"scaling":["Buildings"],"window":["Era"]},
  {"id":"FR4","name":"Fairy Cuisine","faction":"Fairy","tier":2,"cost":"5e11","effect":"Increase the base production of Inns by +234. Reduce building cost multiplier by 0.02 (becomes 1.13).","formula":"","effects":["Specific Buildings","Building Cost Reduction"],"scaling":[],"window":[]},
  {"id":"FR5","name":"Golden Pots","faction":"Fairy","tier":2,"cost":"5e12","effect":"Additively increase clicking reward by 20% of production of Farms, Inns and Blacksmiths combined.","formula":"","effects":["Clicking"],"scaling":["Buildings"],"window":["Era"]},
  {"id":"FR6","name":"Spellsmith","faction":"Fairy","tier":2,"cost":"5e13","effect":"Blacksmiths also increase your Mana Regeneration.","formula":"+(2.75 * x ^ 0.275), where x is Blacksmiths owned","effects":["Mana & Spells"],"scaling":["Buildings"],"window":["Era"]},
  {"id":"FR7","name":"Starmetal Alloys","faction":"Fairy","tier":3,"cost":"5e15","effect":"Increase the base production of Blacksmiths by +580. Reduces cost multiplier by 0.02 (becomes 1.13).","formula":"","effects":["Specific Buildings","Building Cost Reduction"],"scaling":[],"window":[]},
  {"id":"FR8","name":"Rainbow Link","faction":"Fairy","tier":3,"cost":"5e16","effect":"Increase the production of all buildings based on Farms, Inns and Blacksmiths owned.","formula":"(0.75 * x ^ 0.75)%, where x is Farms + Inns + Blacksmiths","effects":["All Buildings"],"scaling":["Buildings"],"window":["Era"]},
  {"id":"FR9","name":"Swarm of Fairies","faction":"Fairy","tier":3,"cost":"5e17","effect":"Gain assistants based on Farms, Inns and Blacksmiths owned.","formula":"+(1.2 * x ^ 0.6), where x is Farms + Inns + Blacksmiths","effects":["Assistants"],"scaling":["Buildings"],"window":["Era"]},
  {"id":"FR10","name":"Bubble Swarm","faction":"Fairy","tier":4,"cost":"1e60","effect":"Increase maximum Mana based on the highest Swarming Towers built this Reincarnation.","formula":"+(x ^ 1.05), where x is highest Swarming Towers this Reincarnation","effects":["Mana & Spells"],"scaling":["Buildings"],"window":["Reincarnation"]},
  {"id":"FR11","name":"Pheromones","faction":"Fairy","tier":4,"cost":"1e80","effect":"Gain assistants additively based on time spent as Chaos this Reincarnation.","formula":"+(80 * x ^ 0.8), where x is Chaos time this Reincarnation","effects":["Assistants"],"scaling":["Activity"],"window":["Reincarnation"]},
  {"id":"FR12","name":"Dream Catchers","faction":"Fairy","tier":4,"cost":"1e95","effect":"Multiplicatively increase Mana Regeneration based on Chaos spells cast this Reincarnation.","formula":"(1.2 * x ^ 0.8)%, where x is Chaos spells cast this Reincarnation","effects":["Mana & Spells"],"scaling":["Mana & Spells"],"window":["Reincarnation"]}
,
  {"id":"EL1","name":"Elven Mint","faction":"Elven","tier":1,"cost":"5e7","effect":"The base chance to find Faction Coins is increased multiplicatively by 150%.","formula":"","effects":["Faction Coins"],"scaling":[],"window":[]},
  {"id":"EL2","name":"Elven Treasure Casing","faction":"Elven","tier":1,"cost":"5e8","effect":"Increase base clicking reward by +25,000 per Trophy unlocked. Increase FC find chance based on Trophies.","formula":"+(1 + 0.1 * x) ^ 0.95)%, where x is Trophies unlocked","effects":["Clicking","Faction Coins"],"scaling":["Progression"],"window":[]},
  {"id":"EL3","name":"Ancient Clicking Arts","faction":"Elven","tier":1,"cost":"5e9","effect":"Increase Mana Regeneration based on clicks made this Reincarnation.","formula":"+(2 * log10(1 + x) ^ 1.25), where x is clicks this Reincarnation","effects":["Mana & Spells"],"scaling":["Activity"],"window":["Reincarnation"]},
  {"id":"EL4","name":"Elven Emissary","faction":"Elven","tier":2,"cost":"5e11","effect":"Increase clicking reward based on Good buildings owned. Assistants find 3x as many Faction Coins.","formula":"(x ^ 0.6)%, where x is Good buildings owned","effects":["Clicking","Faction Coins"],"scaling":["Buildings"],"window":["Era"]},
  {"id":"EL5","name":"Elven Efficiency","faction":"Elven","tier":2,"cost":"5e12","effect":"Increase Royal Exchange bonus based on Faction Coins found this Era.","formula":"+(2 * ln(1 + x) ^ 2)%, where x is FC found this Era","effects":["Coins & Gems"],"scaling":["Coins & Gems"],"window":["Era"]},
  {"id":"EL6","name":"Secret Clicking Techniques","faction":"Elven","tier":2,"cost":"5e13","effect":"Increase the production of all buildings based on clicks made this Reincarnation.","formula":"(2 * x ^ 0.4)%, where x is clicks this Reincarnation","effects":["All Buildings"],"scaling":["Activity"],"window":["Reincarnation"]},
  {"id":"EL7","name":"Elven Diplomacy","faction":"Elven","tier":3,"cost":"5e15","effect":"Clicks count more based on Faction Coins found this Era.","formula":"(2 * ln(1 + x) ^ 2)%, where x is FC found this Era","effects":["Clicking"],"scaling":["Coins & Gems"],"window":["Era"]},
  {"id":"EL8","name":"Elven Luck","faction":"Elven","tier":3,"cost":"5e16","effect":"Each click has a 1% chance to produce 2500% of total production in coins and generate bonus Faction Coins. Assistants trigger this once per second.","formula":"Production: (2500 * (x + y)); FC: (x * (R+1)), where R is reincarnations","effects":["Clicking","Faction Coins"],"scaling":["Progression"],"window":["Reincarnation"]},
  {"id":"EL9","name":"Sylvan Treasure Frills","faction":"Elven","tier":3,"cost":"5e17","effect":"Additively increase base clicking reward by 50% of your building production.","formula":"","effects":["Clicking"],"scaling":["Buildings"],"window":["Era"]},
  {"id":"EL10","name":"Wooden Dice","faction":"Elven","tier":4,"cost":"1e60","effect":"Increase Elven Luck chance and effects based on highest Arboreal Cities this Reincarnation. Also triggers 100,000 Tax Collections on Luck proc.","formula":"Luck chance: +(x ^ 0.4)%; Prod: (40 * x ^ 0.8)%, where x is highest Arboreal Cities","effects":["Clicking","Faction Coins","Mana & Spells"],"scaling":["Buildings"],"window":["Reincarnation"]},
  {"id":"EL11","name":"Camouflage","faction":"Elven","tier":4,"cost":"1e80","effect":"Assistants and Clicks count 1,000% more for all purposes. Increase assistant production based on assistants owned.","formula":"(2 * ln(1 + x) ^ 2)%, where x is assistants owned","effects":["Assistants","Clicking"],"scaling":["Assistants"],"window":["Era"]},
  {"id":"EL12","name":"Elven Discipline","faction":"Elven","tier":4,"cost":"1e95","effect":"Increase assistants additively and multiplicatively based on Faction Coins found this Era.","formula":"+(50 * ln(1 + x) ^ 1.5) additive; (1.5 * log10(1 + x) ^ 1.5)% multiplicative, where x is FC this Era","effects":["Assistants"],"scaling":["Coins & Gems"],"window":["Era"]}
,
  {"id":"AN1","name":"Holy Bells","faction":"Angel","tier":1,"cost":"5e7","effect":"Increase Mana Regeneration based on buildings owned.","formula":"+(1.6 * x ^ 0.4), where x is buildings owned","effects":["Mana & Spells"],"scaling":["Buildings"],"window":["Era"]},
  {"id":"AN2","name":"Angelic Determination","faction":"Angel","tier":1,"cost":"5e8","effect":"Increase production of all buildings based on spells cast this Era. Increase Angel Coins found by 500%.","formula":"(4 * ln(1 + x) ^ 2)%, where x is spells cast this Era","effects":["All Buildings","Faction Coins"],"scaling":["Mana & Spells"],"window":["Era"]},
  {"id":"AN3","name":"Angel Feathers","faction":"Angel","tier":1,"cost":"5e9","effect":"Increase Faction Coin find chance additively based on active spells.","formula":"+(10 * x)%, where x is active spells","effects":["Faction Coins"],"scaling":["Mana & Spells"],"window":[]},
  {"id":"AN4","name":"Guardian Angels","faction":"Angel","tier":2,"cost":"5e11","effect":"Spell casts count 100% more.","formula":"","effects":["Mana & Spells"],"scaling":[],"window":[]},
  {"id":"AN5","name":"Angelic Wisdom","faction":"Angel","tier":2,"cost":"5e12","effect":"Decrease cost of all spells by 50%. Increases offline spell cast amount based on offline Mana Regeneration.","formula":"(10 * log10(1 + x))%, where x is offline Mana Regen","effects":["Mana & Spells","Offline"],"scaling":["Mana & Spells"],"window":[]},
  {"id":"AN6","name":"Archangel Feathers","faction":"Angel","tier":2,"cost":"5e13","effect":"Increase Mana Regeneration multiplicatively by 50%.","formula":"","effects":["Mana & Spells"],"scaling":[],"window":[]},
  {"id":"AN7","name":"Magical Gates","faction":"Angel","tier":3,"cost":"5e15","effect":"Increase Maximum Mana based on time spent as Good this Reincarnation.","formula":"+(3.5 * x ^ 0.7), where x is Good time this Reincarnation","effects":["Mana & Spells"],"scaling":["Activity"],"window":["Reincarnation"]},
  {"id":"AN8","name":"Angelic Dominance","faction":"Angel","tier":3,"cost":"5e16","effect":"Spell durations are increased by 50%.","formula":"","effects":["Mana & Spells"],"scaling":[],"window":[]},
  {"id":"AN9","name":"Wings of Liberty","faction":"Angel","tier":3,"cost":"5e17","effect":"Increase production of all buildings based on Mana Regeneration.","formula":"(4 * ln(1 + x) ^ 2)%, where x is Mana Regeneration","effects":["All Buildings"],"scaling":["Mana & Spells"],"window":[]},
  {"id":"AN10","name":"Angelic Fortress","faction":"Angel","tier":4,"cost":"1e60","effect":"Increase maximum Mana based on highest Holy Sites built this Reincarnation.","formula":"+(x ^ 1.05), where x is highest Holy Sites this Reincarnation","effects":["Mana & Spells"],"scaling":["Buildings"],"window":["Reincarnation"]},
  {"id":"AN11","name":"Sacred Ground","faction":"Angel","tier":4,"cost":"1e80","effect":"Increase spell duration based on time spent as Order this Reincarnation.","formula":"(0.5 * x ^ 0.5)%, where x is Order time this Reincarnation","effects":["Mana & Spells"],"scaling":["Activity"],"window":["Reincarnation"]},
  {"id":"AN12","name":"Divine Providence","faction":"Angel","tier":4,"cost":"1e95","effect":"Increase Mana Regeneration multiplicatively based on spells cast this Era.","formula":"(1.5 * ln(1 + x) ^ 2)%, where x is spells cast this Era","effects":["Mana & Spells"],"scaling":["Mana & Spells"],"window":["Era"]}
,
  {"id":"GB1","name":"Strong Currency","faction":"Goblin","tier":1,"cost":"5e7","effect":"Gain assistants additively based on Faction Coins found this Era.","formula":"+(0.5 * ln(1 + x) ^ 2), where x is FC found this Era","effects":["Assistants"],"scaling":["Coins & Gems"],"window":["Era"]},
  {"id":"GB2","name":"Slave Trading","faction":"Goblin","tier":1,"cost":"5e8","effect":"Increase production of all buildings based on Evil buildings owned.","formula":"(2 * x ^ 0.7)%, where x is Evil buildings owned","effects":["All Buildings"],"scaling":["Buildings"],"window":["Era"]},
  {"id":"GB3","name":"Cheap Materials","faction":"Goblin","tier":1,"cost":"5e9","effect":"Tax Collection is worth more seconds based on buildings owned.","formula":"+(x ^ 0.5), where x is buildings owned","effects":["Mana & Spells"],"scaling":["Buildings"],"window":["Era"]},
  {"id":"GB4","name":"Black Market","faction":"Goblin","tier":2,"cost":"5e11","effect":"Production bonus from gems increased by 150%. Increase offline production based on Tax Collections cast this Era.","formula":"(log10(1 + x) ^ 2)%, where x is Tax Collections this Era","effects":["Coins & Gems","Offline"],"scaling":["Mana & Spells"],"window":["Era"]},
  {"id":"GB5","name":"Goblin Economists","faction":"Goblin","tier":2,"cost":"5e12","effect":"Multiplicatively increase Mana Regeneration based on coins owned.","formula":"(0.75 * log10(1 + x) ^ 1.25)%, where x is coins owned","effects":["Mana & Spells"],"scaling":["Coins & Gems"],"window":["Era"]},
  {"id":"GB6","name":"Hobgoblin Gladiators","faction":"Goblin","tier":2,"cost":"5e13","effect":"Increase production of all buildings based on Tax Collection seconds.","formula":"(12 * ln(1 + x) ^ 3)%, where x is Tax Collection seconds","effects":["All Buildings"],"scaling":["Mana & Spells"],"window":["Era"]},
  {"id":"GB7","name":"Goblin Central Bank","faction":"Goblin","tier":3,"cost":"5e15","effect":"Whenever you cast a spell, also cast a Tax Collection for free.","formula":"","effects":["Mana & Spells"],"scaling":[],"window":[]},
  {"id":"GB8","name":"Fool's Gold","faction":"Goblin","tier":3,"cost":"5e16","effect":"Increase Faction Coin find chance based on highest Witch Conclaves owned this Reincarnation.","formula":"floor(2 * x ^ 0.6)%, where x is highest Witch Conclaves this Reincarnation","effects":["Faction Coins"],"scaling":["Buildings"],"window":["Reincarnation"]},
  {"id":"GB9","name":"Green Fingers Discount","faction":"Goblin","tier":3,"cost":"5e17","effect":"Gain coins randomly every 10 minutes (also offline) based on total production including spells.","formula":"(randRange(1,2500) * production per second)","effects":["Offline","Coins & Gems"],"scaling":["Buildings"],"window":[]},
  {"id":"GB10","name":"Fools Gems","faction":"Goblin","tier":4,"cost":"1e60","effect":"Multiplicatively increase production bonus from Gems based on highest Slave Markets built this Reincarnation.","formula":"(0.5 * x ^ 0.5)%, where x is highest Slave Markets this Reincarnation","effects":["Coins & Gems"],"scaling":["Buildings"],"window":["Reincarnation"]},
  {"id":"GB11","name":"Money is Magic","faction":"Goblin","tier":4,"cost":"1e80","effect":"Increase Mana Regeneration based on Tax Collections cast this Era.","formula":"(2 * ln(1 + x) ^ 2)%, where x is Tax Collections this Era","effects":["Mana & Spells"],"scaling":["Mana & Spells"],"window":["Era"]},
  {"id":"GB12","name":"Lousy Architecture","faction":"Goblin","tier":4,"cost":"1e95","effect":"Reduce Non-Unique building cost multiplier by 0.01 (becomes 1.14). Increase Non-Unique building production based on buildings of same tier.","formula":"(x ^ 0.65)%, where x is buildings of same tier","effects":["All Buildings","Building Cost Reduction"],"scaling":["Buildings"],"window":["Era"]}
,
  {"id":"UD1","name":"The Walking Dead","faction":"Undead","tier":1,"cost":"5e7","effect":"Increase Faction Coin find chance additively based on assistants owned.","formula":"+(ln(1 + x) ^ 1.75)%, where x is assistants owned","effects":["Faction Coins"],"scaling":["Assistants"],"window":["Era"]},
  {"id":"UD2","name":"Deadened Muscles","faction":"Undead","tier":1,"cost":"5e8","effect":"Increase production of all buildings based on highest Necropolises built this Reincarnation.","formula":"(4 * x ^ 0.8)%, where x is highest Necropolises this Reincarnation","effects":["All Buildings"],"scaling":["Buildings"],"window":["Reincarnation"]},
  {"id":"UD3","name":"Death Temples","faction":"Undead","tier":1,"cost":"5e9","effect":"Increase Mana Regeneration additively based on highest Necropolises built this Reincarnation.","formula":"+(x ^ 0.3), where x is highest Necropolises this Reincarnation","effects":["Mana & Spells"],"scaling":["Buildings"],"window":["Reincarnation"]},
  {"id":"UD4","name":"Unholy Rituals","faction":"Undead","tier":2,"cost":"5e11","effect":"Increase offline production based on time spent offline this Reincarnation.","formula":"(0.4 * x ^ 0.8)%, where x is offline time this Reincarnation","effects":["Offline"],"scaling":["Activity"],"window":["Reincarnation"]},
  {"id":"UD5","name":"Corpse Supply","faction":"Undead","tier":2,"cost":"5e12","effect":"Gain assistants based on time spent offline this Reincarnation.","formula":"+(0.4 * x ^ 0.6), where x is offline time this Reincarnation","effects":["Assistants"],"scaling":["Activity"],"window":["Reincarnation"]},
  {"id":"UD6","name":"Plagued Buildings","faction":"Undead","tier":2,"cost":"5e13","effect":"Increase production of all buildings based on time spent this Era.","formula":"(0.75 * x ^ 0.75)%, where x is time this Era","effects":["All Buildings"],"scaling":["Activity"],"window":["Era"]},
  {"id":"UD7","name":"Dead Fields","faction":"Undead","tier":3,"cost":"5e15","effect":"Buildings count 75% more.","formula":"","effects":["All Buildings"],"scaling":[],"window":[]},
  {"id":"UD8","name":"Tireless Workers","faction":"Undead","tier":3,"cost":"5e16","effect":"Increase the production of assistants by 1500%.","formula":"","effects":["Assistants"],"scaling":[],"window":[]},
  {"id":"UD9","name":"Undead Resilience","faction":"Undead","tier":3,"cost":"5e17","effect":"Increases offline production based on Mana Regeneration.","formula":"(125 * ln(1 + x) ^ 2.5)%, where x is Mana Regeneration","effects":["Offline"],"scaling":["Mana & Spells"],"window":[]},
  {"id":"UD10","name":"Flesh Servants","faction":"Undead","tier":4,"cost":"1e60","effect":"Multiplicatively increase assistants based on highest Flesh Workshops built this Reincarnation.","formula":"(1.3 * x ^ 0.7)%, where x is highest Flesh Workshops this Reincarnation","effects":["Assistants"],"scaling":["Buildings"],"window":["Reincarnation"]},
  {"id":"UD11","name":"Eternal Servitude","faction":"Undead","tier":4,"cost":"1e80","effect":"Increase production of Unique buildings based on time spent this Era.","formula":"(x ^ 0.7)%, where x is time this Era","effects":["Specific Buildings"],"scaling":["Activity"],"window":["Era"]},
  {"id":"UD12","name":"Zombie Apocalypse","faction":"Undead","tier":4,"cost":"1e95","effect":"Gain assistants additively based on total offline time this Reincarnation.","formula":"+(21 * x ^ 0.7), where x is offline time this Reincarnation","effects":["Assistants"],"scaling":["Activity"],"window":["Reincarnation"]}
,
  {"id":"DM1","name":"Torture Chambers","faction":"Demon","tier":1,"cost":"5e7","effect":"Increase production of Royal Castles / Evil Fortresses / Iron Strongholds (by alignment) based on assistants owned.","formula":"(6 * ln(1 + x) ^ 3)%, where x is assistants owned","effects":["Specific Buildings"],"scaling":["Assistants"],"window":["Era"]},
  {"id":"DM2","name":"Devil Tyrant","faction":"Demon","tier":1,"cost":"5e8","effect":"The three highest building tiers count more based on time spent as Evil this Reincarnation.","formula":"(1.2 * x ^ 0.4)%, where x is Evil time this Reincarnation","effects":["Specific Buildings"],"scaling":["Activity"],"window":["Reincarnation"]},
  {"id":"DM3","name":"Evil Conquerors","faction":"Demon","tier":1,"cost":"5e9","effect":"Increase production of all buildings based on highest Hell Portals built this Reincarnation.","formula":"(4 * x ^ 0.8)%, where x is highest Hell Portals this Reincarnation","effects":["All Buildings"],"scaling":["Buildings"],"window":["Reincarnation"]},
  {"id":"DM4","name":"Lava Pits","faction":"Demon","tier":2,"cost":"5e11","effect":"Increase base production of Evil Fortresses by +200,000 and Hell Portals by +2,000,000. Playtime this Era counts more by 6 extra hours.","formula":"","effects":["Specific Buildings"],"scaling":[],"window":["Era"]},
  {"id":"DM5","name":"Demon Overseers","faction":"Demon","tier":2,"cost":"5e12","effect":"Increase production of three highest building tiers based on Trophies unlocked.","formula":"(2 * x ^ 0.8)%, where x is trophies unlocked","effects":["Specific Buildings"],"scaling":["Progression"],"window":[]},
  {"id":"DM6","name":"Demonic Presence","faction":"Demon","tier":2,"cost":"5e13","effect":"Increase Maximum Mana additively based on Evil spells cast this Era.","formula":"+(6 * x ^ 0.4), where x is Evil spells cast this Era","effects":["Mana & Spells"],"scaling":["Mana & Spells"],"window":["Era"]},
  {"id":"DM7","name":"Infernal Magic","faction":"Demon","tier":3,"cost":"5e15","effect":"Hell Portals also increase Mana Regeneration.","formula":"+(3.5 * x ^ 0.35), where x is Hell Portals owned","effects":["Mana & Spells"],"scaling":["Buildings"],"window":["Era"]},
  {"id":"DM8","name":"Burning Legion","faction":"Demon","tier":3,"cost":"5e16","effect":"Gain assistants based on Hell Portals owned.","formula":"+(1.5 * x ^ 0.65), where x is Hell Portals owned","effects":["Assistants"],"scaling":["Buildings"],"window":["Era"]},
  {"id":"DM9","name":"Very Bad Guys","faction":"Demon","tier":3,"cost":"5e17","effect":"Increase production of Heaven's Gate / Hell Portals / Ancient Pyramid (by alignment) based on highest Hell Portals this Reincarnation.","formula":"(4 * x ^ 0.8)%, where x is highest Hell Portals this Reincarnation","effects":["Specific Buildings"],"scaling":["Buildings"],"window":["Reincarnation"]},
  {"id":"DM10","name":"Abyssal Furnace","faction":"Demon","tier":4,"cost":"1e60","effect":"Increase production of all buildings based on highest Burning Abysses this Reincarnation. Higher tiers get better bonuses.","formula":"(0.5 * T ^ 1.5 * x ^ 0.5)%, where T is tier, x is highest Burning Abysses this Reincarnation","effects":["All Buildings"],"scaling":["Buildings"],"window":["Reincarnation"]},
  {"id":"DM11","name":"Demonic Fury","faction":"Demon","tier":4,"cost":"1e80","effect":"Multiplicatively increase FC find chance based on minimum of Evil and Chaos time this Reincarnation.","formula":"(0.25 * min(x, y) ^ 0.75)%, where x is Evil time, y is Chaos time this Reincarnation","effects":["Faction Coins"],"scaling":["Activity"],"window":["Reincarnation"]},
  {"id":"DM12","name":"Devastation","faction":"Demon","tier":4,"cost":"1e95","effect":"Increase production of three highest building tiers based on Mana Regeneration.","formula":"(2.5 * ln(1 + x) ^ 2.5)%, where x is Mana Regeneration","effects":["Specific Buildings"],"scaling":["Mana & Spells"],"window":[]}
,
  {"id":"TT1","name":"Colossal Forge","faction":"Titan","tier":1,"cost":"5e20","effect":"Increase production of all buildings based on buildings owned.","formula":"(6 * x ^ 0.6)%, where x is buildings owned","effects":["All Buildings"],"scaling":["Buildings"],"window":["Era"]},
  {"id":"TT2","name":"Charged Clicks","faction":"Titan","tier":1,"cost":"5e21","effect":"Multiplicatively increase Mana Regeneration based on clicks made this Era.","formula":"(25 + 2.5 * log10(1 + x) ^ 2.5 + x ^ 0.25)%, where x is clicks this Era","effects":["Mana & Spells"],"scaling":["Activity"],"window":["Era"]},
  {"id":"TT3","name":"Titan Obelisk","faction":"Titan","tier":1,"cost":"5e22","effect":"Increase Faction Coin find chance additively based on Neutral time this Reincarnation.","formula":"+(3 * x ^ 0.7)%, where x is Neutral time this Reincarnation","effects":["Faction Coins"],"scaling":["Activity"],"window":["Reincarnation"]},
  {"id":"TT4","name":"Titan Drill","faction":"Titan","tier":2,"cost":"5e24","effect":"Increase base production of Warrior Barracks/Slave Pens/Deep Mines by +9,635 and Cathedrals/Dark Temples/Monasteries by +98,000 (by alignment). Also increase those tiers' production by 1,000%.","formula":"","effects":["Specific Buildings"],"scaling":[],"window":[]},
  {"id":"TT5","name":"Charged Structures","faction":"Titan","tier":2,"cost":"5e25","effect":"Increase production of all buildings based on active spells.","formula":"(15 * x)%, where x is active spells","effects":["All Buildings"],"scaling":["Mana & Spells"],"window":[]},
  {"id":"TT6","name":"Titan Sized Walls","faction":"Titan","tier":2,"cost":"5e26","effect":"Increase Hall of Legends production based on assistants owned.","formula":"(20 + 2.15 * ln(1 + x) ^ 2.15)%, where x is assistants owned","effects":["Specific Buildings"],"scaling":["Assistants"],"window":["Era"]},
  {"id":"TT7","name":"Cyclopean Strength","faction":"Titan","tier":3,"cost":"5e28","effect":"Assistants count 200% more, and their production is increased by 200%.","formula":"","effects":["Assistants"],"scaling":[],"window":[]},
  {"id":"TT8","name":"Heavy Coins","faction":"Titan","tier":3,"cost":"5e29","effect":"Royal Exchanges production bonus increased by additional 100% each. Reduces Royal Exchange cost multiplier by 0.01 (becomes 1.09).","formula":"","effects":["Coins & Gems","Building Cost Reduction"],"scaling":[],"window":[]},
  {"id":"TT9","name":"Oversized Legends","faction":"Titan","tier":3,"cost":"5e30","effect":"Reduce Hall of Legends cost multiplier by 0.01 (becomes 1.14). Increase assistant production based on Halls of Legends built.","formula":"(6 * x ^ 0.6)%, where x is Halls of Legends built","effects":["Assistants","Building Cost Reduction"],"scaling":["Buildings"],"window":["Era"]},
  {"id":"TT10","name":"Giant Market","faction":"Titan","tier":4,"cost":"1e60","effect":"Royal Exchanges count more based on highest Mountain Palaces built this Reincarnation.","formula":"(x ^ 0.7)%, where x is highest Mountain Palaces this Reincarnation","effects":["Coins & Gems"],"scaling":["Buildings"],"window":["Reincarnation"]},
  {"id":"TT11","name":"Titanic Authority","faction":"Titan","tier":4,"cost":"1e80","effect":"Increase production of Unique Buildings based on Royal Exchanges made.","formula":"(x ^ 0.6)%, where x is Royal Exchanges bought","effects":["Specific Buildings"],"scaling":["Coins & Gems"],"window":["Era"]},
  {"id":"TT12","name":"Colossus Kingdom","faction":"Titan","tier":4,"cost":"1e95","effect":"Gain assistants based on time spent as Order this Reincarnation.","formula":"+(25 * x ^ 0.7), where x is Order time this Reincarnation","effects":["Assistants"],"scaling":["Activity"],"window":["Reincarnation"]}
,
  {"id":"DD1","name":"Druidic Vocabulary","faction":"Druid","tier":1,"cost":"5e20","effect":"Increase production of all buildings by tier, best bonus to lowest.","formula":"(4000 * (12 - T))%, where T is building tier","effects":["All Buildings"],"scaling":[],"window":[]},
  {"id":"DD2","name":"Animal Companions","faction":"Druid","tier":1,"cost":"5e21","effect":"Instantly gain 3 Animal assistants; more come based on time this Era.","formula":"+(3 + 1.75 * x ^ 0.5), where x is time this Era","effects":["Assistants"],"scaling":["Activity"],"window":["Era"]},
  {"id":"DD3","name":"Natural Recycling","faction":"Druid","tier":1,"cost":"5e22","effect":"Increase Faction Coin find chance additively and multiplicatively based on total buildings owned.","formula":"(0.4 * x ^ 0.4)% additive+multiplicative, where x is buildings owned","effects":["Faction Coins"],"scaling":["Buildings"],"window":["Era"]},
  {"id":"DD4","name":"Earthly Bond","faction":"Druid","tier":2,"cost":"5e24","effect":"Increase Maximum Mana additively based on highest Stone Pillars built this Reincarnation.","formula":"+(2 * x), where x is highest Stone Pillars this Reincarnation","effects":["Mana & Spells"],"scaling":["Buildings"],"window":["Reincarnation"]},
  {"id":"DD5","name":"Bardic Knowledge","faction":"Druid","tier":2,"cost":"5e25","effect":"Increase production of all buildings based on Maximum Mana.","formula":"(16 * ln(1 + x) ^ 2)%, where x is Maximum Mana","effects":["All Buildings"],"scaling":["Mana & Spells"],"window":[]},
  {"id":"DD6","name":"Shapeshifting","faction":"Druid","tier":2,"cost":"5e26","effect":"Increase Mana Regeneration additively based on assistants owned.","formula":"+(1.3 * x ^ 0.7), where x is assistants owned","effects":["Mana & Spells"],"scaling":["Assistants"],"window":["Era"]},
  {"id":"DD7","name":"Mabinogion","faction":"Druid","tier":3,"cost":"5e28","effect":"Increase production of Non-Unique buildings by tier, best bonus to lowest.","formula":"(12 * 1.8 ^ (12 - T))%, where T is building tier","effects":["All Buildings"],"scaling":[],"window":[]},
  {"id":"DD8","name":"Earthly Soul","faction":"Druid","tier":3,"cost":"5e29","effect":"Increase Mana Regeneration additively based on highest Stone Pillars this Reincarnation.","formula":"+(x ^ 0.25), where x is highest Stone Pillars this Reincarnation","effects":["Mana & Spells"],"scaling":["Buildings"],"window":["Reincarnation"]},
  {"id":"DD9","name":"Building Jungle","faction":"Druid","tier":3,"cost":"5e30","effect":"Increase production of each building based on buildings of the same type owned.","formula":"(1.5 * x ^ 0.9)%, where x is buildings of same type","effects":["All Buildings"],"scaling":["Buildings"],"window":["Era"]},
  {"id":"DD10","name":"Building Vines","faction":"Druid","tier":4,"cost":"1e60","effect":"Increase spell duration based on highest Ziggurats built this Reincarnation.","formula":"(0.5 * x ^ 0.5)%, where x is highest Ziggurats this Reincarnation","effects":["Mana & Spells"],"scaling":["Buildings"],"window":["Reincarnation"]},
  {"id":"DD11","name":"Lunar Cycle","faction":"Druid","tier":4,"cost":"1e80","effect":"Increase Maximum Mana additively by online time this Era; multiplicatively by offline time this Era.","formula":"+(50 * x ^ 0.85) online; (0.5 * y ^ 0.5)% offline, where x/y are online/offline time this Era","effects":["Mana & Spells"],"scaling":["Activity"],"window":["Era"]},
  {"id":"DD12","name":"Grove Farming","faction":"Druid","tier":4,"cost":"1e95","effect":"Increase production of all buildings by tier; middle tiers get best bonus.","formula":"(0.8 * ((6 - abs(6 - T)) ^ 4))%, where T is building tier","effects":["All Buildings"],"scaling":[],"window":[]}
,
  {"id":"FC1","name":"Territorial Expanse","faction":"Faceless","tier":1,"cost":"5e20","effect":"Increase production of Citadels / Necropolises / Labyrinths (by alignment) based on assistants owned.","formula":"(50 * ln(1 + x) ^ 2.5)%, where x is assistants owned","effects":["Specific Buildings"],"scaling":["Assistants"],"window":["Era"]},
  {"id":"FC2","name":"Evolutive Mutation","faction":"Faceless","tier":1,"cost":"5e21","effect":"Increase Faction Coin find chance based on highest Labyrinths built this Reincarnation.","formula":"floor(3 * x ^ 0.6)%, where x is highest Labyrinths this Reincarnation","effects":["Faction Coins"],"scaling":["Buildings"],"window":["Reincarnation"]},
  {"id":"FC3","name":"Deep Memory","faction":"Faceless","tier":1,"cost":"5e22","effect":"Multiplicatively increase assistants based on longest game session this Reincarnation.","formula":"(0.3 * x ^ 0.7)%, where x is longest session this Reincarnation","effects":["Assistants"],"scaling":["Activity"],"window":["Reincarnation"]},
  {"id":"FC4","name":"Gold Synthesis","faction":"Faceless","tier":2,"cost":"5e24","effect":"Increase production of Neutral buildings based on coins owned.","formula":"(0.2 * ln(1 + x) ^ 2)%, where x is coins owned","effects":["Specific Buildings"],"scaling":["Coins & Gems"],"window":["Era"]},
  {"id":"FC5","name":"Mitosis","faction":"Faceless","tier":2,"cost":"5e25","effect":"Gain Faceless Assistants based on buildings owned.","formula":"floor(0.5 * x ^ 0.5), where x is buildings owned","effects":["Assistants"],"scaling":["Buildings"],"window":["Era"]},
  {"id":"FC6","name":"Overgrowth","faction":"Faceless","tier":2,"cost":"5e26","effect":"Increase production based on highest buildings purchased in a single game this Reincarnation.","formula":"(0.8 * x ^ 0.8)%, where x is highest single-game buildings this Reincarnation","effects":["All Buildings"],"scaling":["Buildings"],"window":["Reincarnation"]},
  {"id":"FC7","name":"Magical Treasure","faction":"Faceless","tier":3,"cost":"5e28","effect":"Increase Mana Regeneration based on assistants owned.","formula":"+(2.5 * x ^ 0.5), where x is assistants owned","effects":["Mana & Spells"],"scaling":["Assistants"],"window":["Era"]},
  {"id":"FC8","name":"Abominations","faction":"Faceless","tier":3,"cost":"5e29","effect":"Increase production of assistants based on active spells.","formula":"(20 * x ^ 0.9)%, where x is active spells","effects":["Assistants"],"scaling":["Mana & Spells"],"window":[]},
  {"id":"FC9","name":"Hive Mind","faction":"Faceless","tier":3,"cost":"5e30","effect":"Increase production based on total time affiliated with Faceless (All Time, persists through Reincarnations).","formula":"(x ^ 0.5)%, where x is Faceless time (All Time)","effects":["All Buildings"],"scaling":["Activity"],"window":["All Time"]},
  {"id":"FC10","name":"Primal Knowledge","faction":"Faceless","tier":4,"cost":"1e60","effect":"Multiplicatively increase FC find chance based on highest Forbidden Libraries this Reincarnation. Grows over time, resets every 15 minutes.","formula":"((t % 900) / 75 * x ^ 0.4)%, t is time this Era, x is highest Forbidden Libraries","effects":["Faction Coins"],"scaling":["Buildings","Activity"],"window":["Era","Reincarnation"]},
  {"id":"FC11","name":"Forbidden Language","faction":"Faceless","tier":4,"cost":"1e80","effect":"Increase spell durations based on Reincarnations made.","formula":"(0.8 * x ^ 0.8)%, where x is Reincarnations made","effects":["Mana & Spells"],"scaling":["Progression"],"window":[]},
  {"id":"FC12","name":"Dimension Door","faction":"Faceless","tier":4,"cost":"1e95","effect":"Increase production of all buildings based on highest Maximum Mana this Reincarnation.","formula":"(2 * ln(1 + x) ^ 2)%, where x is highest Max Mana this Reincarnation","effects":["All Buildings"],"scaling":["Mana & Spells"],"window":["Reincarnation"]}
,
  {"id":"DN1","name":"Dwarven Ale","faction":"Dwarven","tier":1,"cost":"5e45","effect":"Increase Faction Coin find chance (additive) based on Blacksmiths owned.","formula":"+(2 * x ^ 0.5)%, where x is Blacksmiths owned","effects":["Faction Coins"],"scaling":["Buildings"],"window":["Era"]},
  {"id":"DN2","name":"Expert Masonry","faction":"Dwarven","tier":1,"cost":"5e46","effect":"Reduce all building cost multipliers by 0.01 (becomes 1.14).","formula":"","effects":["Building Cost Reduction"],"scaling":[],"window":[]},
  {"id":"DN3","name":"Mining Prodigies","faction":"Dwarven","tier":1,"cost":"5e47","effect":"Increase production of all buildings based on Excavations made (including resets) this Reincarnation.","formula":"(40 * (x * (1 + 2 * y)) ^ 0.4)%, where x is excavations, y is resets this Reincarnation","effects":["All Buildings"],"scaling":["Misc"],"window":["Reincarnation"]},
  {"id":"DN4","name":"Underground Citadels","faction":"Dwarven","tier":2,"cost":"5e49","effect":"Multiplicatively increase Mana Regeneration based on Gems owned.","formula":"(1.5 * log10(1 + x) ^ 1.5)%, where x is Gems owned","effects":["Mana & Spells"],"scaling":["Coins & Gems"],"window":["Era"]},
  {"id":"DN5","name":"Indestructible Treasure","faction":"Dwarven","tier":2,"cost":"5e50","effect":"Increase clicking reward based on buildings owned.","formula":"(0.5 * x ^ 0.65)%, where x is buildings owned","effects":["Clicking"],"scaling":["Buildings"],"window":["Era"]},
  {"id":"DN6","name":"Bearded Assistants","faction":"Dwarven","tier":2,"cost":"5e51","effect":"Increase production of assistants based on time this Era (beard grows!).","formula":"(x ^ 0.7)%, where x is time this Era","effects":["Assistants"],"scaling":["Activity"],"window":["Era"]},
  {"id":"DN7","name":"Battlehammers","faction":"Dwarven","tier":3,"cost":"5e53","effect":"Increase production of all buildings based on Dwarven Coins found this Era.","formula":"(2 * ln(1 + x) ^ 2)%, where x is Dwarven Coins found this Era","effects":["All Buildings"],"scaling":["Faction Coins"],"window":["Era"]},
  {"id":"DN8","name":"Magic Resistance","faction":"Dwarven","tier":3,"cost":"5e54","effect":"Reduce Excavation cost multiplier by 0.02 (becomes 1.18).","formula":"","effects":["Building Cost Reduction"],"scaling":[],"window":[]},
  {"id":"DN9","name":"Overwatch","faction":"Dwarven","tier":3,"cost":"5e55","effect":"Increase Maximum Mana based on duration of your longest spell.","formula":"+(50 + 35 * x ^ 0.7), where x is longest spell duration","effects":["Mana & Spells"],"scaling":["Mana & Spells"],"window":[]},
  {"id":"DN10","name":"Solidity","faction":"Dwarven","tier":4,"cost":"1e100","effect":"Multiplicatively increase production bonus from Gems based on highest High Bastions this Reincarnation.","formula":"(1.6 * x ^ 0.6)%, where x is highest High Bastions this Reincarnation","effects":["Coins & Gems"],"scaling":["Buildings"],"window":["Reincarnation"]},
  {"id":"DN11","name":"Stonetalking","faction":"Dwarven","tier":4,"cost":"1e110","effect":"Increase production of all buildings based on higher of Maximum Mana or Mana Regeneration.","formula":"(2 * ln(1 + max(x, y)) ^ 2)%, where x is Max Mana, y is Mana Regen","effects":["All Buildings"],"scaling":["Mana & Spells"],"window":[]},
  {"id":"DN12","name":"Refined Minerals","faction":"Dwarven","tier":4,"cost":"1e120","effect":"Multiplicatively increase Mana Regen and Max Mana based on highest time as Order, Balance, or Chaos.","formula":"(0.03 * max(x, y, z) ^ 0.7)%, where x/y/z are Order/Balance/Chaos time this Reincarnation","effects":["Mana & Spells"],"scaling":["Activity"],"window":["Reincarnation"]}
,
  {"id":"DW1","name":"Underworld Tyranny","faction":"Drow","tier":1,"cost":"5e45","effect":"Increase production of all buildings based on total Evil time this Reincarnation.","formula":"(0.7 * x ^ 0.7)%, where x is Evil time this Reincarnation","effects":["All Buildings"],"scaling":["Activity"],"window":["Reincarnation"]},
  {"id":"DW2","name":"Honor Among Killers","faction":"Drow","tier":1,"cost":"5e46","effect":"Increase Faction Coin find chance (additive) based on assistants owned.","formula":"+(100 + 0.5 * x ^ 0.5)%, where x is assistants owned","effects":["Faction Coins"],"scaling":["Assistants"],"window":["Era"]},
  {"id":"DW3","name":"Shadow Advance","faction":"Drow","tier":1,"cost":"5e47","effect":"Increase production of all buildings based on Maximum Mana.","formula":"(2 * log10(1 + x) ^ 2)%, where x is Maximum Mana","effects":["All Buildings"],"scaling":["Mana & Spells"],"window":[]},
  {"id":"DW4","name":"Mana Addicts","faction":"Drow","tier":2,"cost":"5e49","effect":"Mana Regeneration increases over time this Era.","formula":"+(2.5 + 0.25 * x ^ 0.5), where x is time this Era","effects":["Mana & Spells"],"scaling":["Activity"],"window":["Era"]},
  {"id":"DW5","name":"Blood Sacrifices","faction":"Drow","tier":2,"cost":"5e50","effect":"Increase production of all buildings based on highest Dark Temples this Reincarnation.","formula":"(3 * x)%, where x is highest Dark Temples this Reincarnation","effects":["All Buildings"],"scaling":["Buildings"],"window":["Reincarnation"]},
  {"id":"DW6","name":"Blackmail","faction":"Drow","tier":2,"cost":"5e51","effect":"Reduce Royal Exchange cost multiplier by 0.02 (becomes 1.08).","formula":"","effects":["Building Cost Reduction"],"scaling":[],"window":[]},
  {"id":"DW7","name":"Spider Gods","faction":"Drow","tier":3,"cost":"5e53","effect":"Multiplicatively increase assistants based on buildings owned.","formula":"(0.5 * x ^ 0.5)%, where x is buildings owned","effects":["Assistants"],"scaling":["Buildings"],"window":["Era"]},
  {"id":"DW8","name":"Professional Assassins","faction":"Drow","tier":3,"cost":"5e54","effect":"Multiplicatively increase production bonus from Gems based on Royal Exchanges made.","formula":"(0.6 * x ^ 0.6)%, where x is Royal Exchanges made","effects":["Coins & Gems"],"scaling":["Coins & Gems"],"window":["Era"]},
  {"id":"DW9","name":"Blade Dance","faction":"Drow","tier":3,"cost":"5e55","effect":"Increase production of all buildings based on Combo Strike counter this Era.","formula":"(100 + 80 * x ^ 0.4)%, where x is Combo Strike counter this Era","effects":["All Buildings"],"scaling":["Mana & Spells"],"window":["Era"]},
  {"id":"DW10","name":"Spider Clerics","faction":"Drow","tier":4,"cost":"1e100","effect":"Increase Royal Exchange bonus (additive) based on highest Brothels this Reincarnation.","formula":"+(1.75 * x ^ 0.75)%, where x is highest Brothels this Reincarnation","effects":["Coins & Gems"],"scaling":["Buildings"],"window":["Reincarnation"]},
  {"id":"DW11","name":"Ancillae Obscurae","faction":"Drow","tier":4,"cost":"1e110","effect":"Increase Non-Unique building production based on Unique Buildings owned.","formula":"(50 * x ^ 0.5)%, where x is Unique Buildings owned","effects":["All Buildings"],"scaling":["Buildings"],"window":["Era"]},
  {"id":"DW12","name":"Crystal Servants","faction":"Drow","tier":4,"cost":"1e120","effect":"Multiplicatively gain assistants based on current gems.","formula":"(1.75 * log10(1 + x) ^ 1.75)%, where x is gems owned","effects":["Assistants"],"scaling":["Coins & Gems"],"window":["Era"]}
,
  {"id":"MC1","name":"Mercenary First Contract","faction":"Mercenary","tier":1,"cost":"5e55","effect":"Unlocks Tier 1. Choose a spell and 4 faction upgrades from any faction matching your alignment.","formula":"","effects":[],"scaling":[],"window":[]},
  {"id":"MC2","name":"Mercenary Second Contract","faction":"Mercenary","tier":2,"cost":"2.5e64","effect":"Unlocks Tier 2. Holy Crusaders (Good): gain Crusader Assistants from spells cast + clicking power. Heresiarchs (Evil): boost Evil buildings by most-built. Trade Lords (Neutral): assistants find all FC types; Mana Regen from FC found.","formula":"Crusaders: +(0.5 * ((1+0.8*x)^(0.5+0.05*A)-1)); Trade Lords: floor(10*log10(1+x^1.5))/10","effects":["Assistants","Specific Buildings","Faction Coins","Mana & Spells"],"scaling":["Activity","Coins & Gems","Buildings"],"window":["Era"]},
  {"id":"MC3","name":"Mercenary Third Contract","faction":"Mercenary","tier":3,"cost":"5e72","effect":"Unlocks Tier 3 and a second spell slot from any faction.","formula":"","effects":[],"scaling":[],"window":[]}
,
  {"id":"AR1","name":"Star Trading","faction":"Archon","tier":1,"cost":"1e150","effect":"Increase production of all buildings based on highest Royal Exchanges made this Reincarnation.","formula":"(0.9 * x)%, where x is highest Royal Exchanges this Reincarnation","effects":["All Buildings"],"scaling":["Coins & Gems"],"window":["Reincarnation"]},
  {"id":"AR2","name":"Energy Recharge","faction":"Archon","tier":1,"cost":"1e151","effect":"Maximum Mana counts more based on Order time this Reincarnation. Also improves Precognition and sets duration to 5 min.","formula":"(0.25 * x ^ 0.5)%, where x is Order time this Reincarnation","effects":["Mana & Spells"],"scaling":["Activity"],"window":["Reincarnation"]},
  {"id":"AR3","name":"Cosmic Resonance","faction":"Archon","tier":1,"cost":"1e152","effect":"Increase Royal Exchange bonus based on clicks this Reincarnation.","formula":"+(0.5 * x ^ 0.5)%, where x is clicks this Reincarnation","effects":["Coins & Gems"],"scaling":["Activity"],"window":["Reincarnation"]},
  {"id":"AR4","name":"Constellation","faction":"Archon","tier":2,"cost":"1e158","effect":"Multiplicatively increase Mana Regeneration based on Unique Buildings owned.","formula":"(0.5 * x ^ 0.5)%, where x is Unique Buildings owned","effects":["Mana & Spells"],"scaling":["Buildings"],"window":["Era"]},
  {"id":"AR5","name":"Archon Pride","faction":"Archon","tier":2,"cost":"1e159","effect":"Multiplicatively increase assistants based on current Lineage level.","formula":"(x)%, where x is current Lineage level","effects":["Assistants"],"scaling":["Progression"],"window":[]},
  {"id":"AR6","name":"Absent-mindedness","faction":"Archon","tier":2,"cost":"1e160","effect":"Increase Offline bonus based on Excavation Resets this Reincarnation.","formula":"(30 + 3 * (x + y) ^ 3)%, where x is free resets, y is ruby resets this Reincarnation","effects":["Offline"],"scaling":["Misc"],"window":["Reincarnation"]},
  {"id":"AR7","name":"Superior Consciousness","faction":"Archon","tier":3,"cost":"1e163","effect":"Increase production of Unique buildings based on their quantity.","formula":"(x)%, where x is Unique Buildings owned","effects":["Specific Buildings"],"scaling":["Buildings"],"window":["Era"]},
  {"id":"AR8","name":"Strange Attraction","faction":"Archon","tier":3,"cost":"1e164","effect":"Multiplicatively increase FC find chance based on activity time of your least-used spell.","formula":"(100 + 0.8 * x ^ 0.8)%, where x is least-used spell activity time this Reincarnation","effects":["Faction Coins"],"scaling":["Mana & Spells"],"window":["Reincarnation"]},
  {"id":"AR9","name":"Arcane Core","faction":"Archon","tier":3,"cost":"1e165","effect":"Increase production of all buildings based on mana produced this Reincarnation.","formula":"(2.5 * log10(1 + x) ^ 2.5)%, where x is mana produced this Reincarnation","effects":["All Buildings"],"scaling":["Mana & Spells"],"window":["Reincarnation"]},
  {"id":"AR10","name":"Purity of Form","faction":"Archon","tier":4,"cost":"1e170","effect":"Lineage levels count 200% more for all purposes.","formula":"","effects":["Progression"],"scaling":[],"window":[]},
  {"id":"AR11","name":"Absolute Hierarchy","faction":"Archon","tier":4,"cost":"1e171","effect":"Remove 1 Ascension Penalty from Call to Arms.","formula":"","effects":["Mana & Spells"],"scaling":[],"window":[]},
  {"id":"AR12","name":"Essence Extractor","faction":"Archon","tier":4,"cost":"1e172","effect":"Multiplicatively increase production bonus from Gems based on duration of longest spell.","formula":"(0.15 * x ^ 0.7)%, where x is longest spell duration","effects":["Coins & Gems"],"scaling":["Mana & Spells"],"window":[]}
,
  {"id":"DJ1","name":"The Desire Within","faction":"Djinn","tier":1,"cost":"1e150","effect":"Increase production of all buildings based on spells of your current alignment cast this Era.","formula":"(25 * ln(1 + x) ^ 2.5)%, where x is alignment spells cast this Era","effects":["All Buildings"],"scaling":["Mana & Spells"],"window":["Era"]},
  {"id":"DJ2","name":"Forbidden Will","faction":"Djinn","tier":1,"cost":"1e151","effect":"Multiplicatively increase FC find chance based on highest FC found this Reincarnation.","formula":"(0.2 * log10(1 + x) ^ 2)%, where x is highest FC found this Reincarnation","effects":["Faction Coins"],"scaling":["Coins & Gems"],"window":["Reincarnation"]},
  {"id":"DJ3","name":"Magical Circuit","faction":"Djinn","tier":1,"cost":"1e152","effect":"Multiplicatively increase Maximum Mana based on researches selected.","formula":"(sum(sumOfDigits(x)) ^ 1.15)%, where x is any selected research upgrade","effects":["Mana & Spells"],"scaling":["Misc"],"window":[]},
  {"id":"DJ4","name":"Wish Upon a Star","faction":"Djinn","tier":2,"cost":"1e158","effect":"[NEEDS REVIEW — T2–T4 not captured from wiki fetch]","formula":"","effects":[],"scaling":[],"window":[]},
  {"id":"DJ5","name":"Djinn T2-2","faction":"Djinn","tier":2,"cost":"NEEDS REVIEW","effect":"[NEEDS REVIEW]","formula":"","effects":[],"scaling":[],"window":[]},
  {"id":"DJ6","name":"Djinn T2-3","faction":"Djinn","tier":2,"cost":"NEEDS REVIEW","effect":"[NEEDS REVIEW]","formula":"","effects":[],"scaling":[],"window":[]},
  {"id":"DJ7","name":"Djinn T3-1","faction":"Djinn","tier":3,"cost":"NEEDS REVIEW","effect":"[NEEDS REVIEW]","formula":"","effects":[],"scaling":[],"window":[]},
  {"id":"DJ8","name":"Djinn T3-2","faction":"Djinn","tier":3,"cost":"NEEDS REVIEW","effect":"[NEEDS REVIEW]","formula":"","effects":[],"scaling":[],"window":[]},
  {"id":"DJ9","name":"Djinn T3-3","faction":"Djinn","tier":3,"cost":"NEEDS REVIEW","effect":"[NEEDS REVIEW]","formula":"","effects":[],"scaling":[],"window":[]},
  {"id":"DJ10","name":"Djinn T4-1","faction":"Djinn","tier":4,"cost":"NEEDS REVIEW","effect":"[NEEDS REVIEW]","formula":"","effects":[],"scaling":[],"window":[]},
  {"id":"DJ11","name":"Djinn T4-2","faction":"Djinn","tier":4,"cost":"NEEDS REVIEW","effect":"[NEEDS REVIEW]","formula":"","effects":[],"scaling":[],"window":[]},
  {"id":"DJ12","name":"Djinn T4-3","faction":"Djinn","tier":4,"cost":"NEEDS REVIEW","effect":"[NEEDS REVIEW]","formula":"","effects":[],"scaling":[],"window":[]}
,
  {"id":"MK1","name":"Hand of the Makers","faction":"Makers","tier":1,"cost":"1e150","effect":"Multiplicatively increase FC find chance based on clicks this Reincarnation.","formula":"(0.5 * x ^ 0.5)%, where x is clicks this Reincarnation","effects":["Faction Coins"],"scaling":["Activity"],"window":["Reincarnation"]},
  {"id":"MK2","name":"Everlasting Materials","faction":"Makers","tier":1,"cost":"1e151","effect":"Increase production of all buildings based on highest buildings built this Reincarnation.","formula":"(0.25 * x ^ 0.85)%, where x is highest buildings built this Reincarnation","effects":["All Buildings"],"scaling":["Buildings"],"window":["Reincarnation"]},
  {"id":"MK3","name":"Infinite Improvements","faction":"Makers","tier":1,"cost":"1e152","effect":"Increase production of all buildings based on Balance time this Reincarnation.","formula":"(0.3 * x ^ 0.7)%, where x is Balance time this Reincarnation","effects":["All Buildings"],"scaling":["Activity"],"window":["Reincarnation"]},
  {"id":"MK4","name":"Makers T2-1","faction":"Makers","tier":2,"cost":"NEEDS REVIEW","effect":"[NEEDS REVIEW — T2–T4 not captured from wiki fetch]","formula":"","effects":[],"scaling":[],"window":[]},
  {"id":"MK5","name":"Makers T2-2","faction":"Makers","tier":2,"cost":"NEEDS REVIEW","effect":"[NEEDS REVIEW]","formula":"","effects":[],"scaling":[],"window":[]},
  {"id":"MK6","name":"Makers T2-3","faction":"Makers","tier":2,"cost":"NEEDS REVIEW","effect":"[NEEDS REVIEW]","formula":"","effects":[],"scaling":[],"window":[]},
  {"id":"MK7","name":"Makers T3-1","faction":"Makers","tier":3,"cost":"NEEDS REVIEW","effect":"[NEEDS REVIEW]","formula":"","effects":[],"scaling":[],"window":[]},
  {"id":"MK8","name":"Makers T3-2","faction":"Makers","tier":3,"cost":"NEEDS REVIEW","effect":"[NEEDS REVIEW]","formula":"","effects":[],"scaling":[],"window":[]},
  {"id":"MK9","name":"Makers T3-3","faction":"Makers","tier":3,"cost":"NEEDS REVIEW","effect":"[NEEDS REVIEW]","formula":"","effects":[],"scaling":[],"window":[]},
  {"id":"MK10","name":"Makers T4-1","faction":"Makers","tier":4,"cost":"NEEDS REVIEW","effect":"[NEEDS REVIEW]","formula":"","effects":[],"scaling":[],"window":[]},
  {"id":"MK11","name":"Makers T4-2","faction":"Makers","tier":4,"cost":"NEEDS REVIEW","effect":"[NEEDS REVIEW]","formula":"","effects":[],"scaling":[],"window":[]},
  {"id":"MK12","name":"Makers T4-3","faction":"Makers","tier":4,"cost":"NEEDS REVIEW","effect":"[NEEDS REVIEW]","formula":"","effects":[],"scaling":[],"window":[]}
]
