[
  {
    "id": "DD1",
    "name": "Druidic Vocabulary",
    "faction": "Druid",
    "tier": 1,
    "cost": "5e20",
    "effect": "Increase production of all buildings based on their tier, giving the best bonus to the lowest.",
    "formula": "(1,000 * (12 - T))%, where T = building tier (1=Farms, 11=HoL)",
    "effects": [
      "All Buildings"
    ],
    "scaling": [],
    "window": []
  },
  {
    "id": "DD2",
    "name": "Animal Companions",
    "faction": "Druid",
    "tier": 1,
    "cost": "5e21",
    "effect": "Gain assistants based on time this Era.",
    "formula": "+(3 + 1.75 * x^0.5), where x = time this Era",
    "effects": [
      "Assistant Amount"
    ],
    "scaling": [
      "Time Played"
    ],
    "window": [
      "Era"
    ]
  },
  {
    "id": "DD3",
    "name": "Natural Recycling",
    "faction": "Druid",
    "tier": 1,
    "cost": "5e22",
    "effect": "Increase Faction Coin find chance additively and multiplicatively based on buildings built.",
    "formula": "Additive: +(6 * x^0.6)%; Mult: (0.5 * x^0.5)%; x = buildings built",
    "effects": [
      "FC Find Chance"
    ],
    "scaling": [
      "Buildings Owned"
    ],
    "window": [
      "Era"
    ]
  },
  {
    "id": "DD4",
    "name": "Earthly Bond",
    "faction": "Druid",
    "tier": 2,
    "cost": "5e24",
    "effect": "Increase Maximum Mana additively based on highest Stone Pillars built this Reincarnation.",
    "formula": "+(2 * x), where x = highest Stone Pillars this Reincarnation",
    "effects": [
      "Max Mana"
    ],
    "scaling": [
      "Specific Building Count"
    ],
    "window": [
      "Reincarnation"
    ]
  },
  {
    "id": "DD5",
    "name": "Bardic Knowledge",
    "faction": "Druid",
    "tier": 2,
    "cost": "5e25",
    "effect": "Increase production of all buildings based on Maximum Mana.",
    "formula": "(15 * ln(1+x)^2.5)%, where x = Maximum Mana",
    "effects": [
      "All Buildings"
    ],
    "scaling": [
      "Max Mana"
    ],
    "window": []
  },
  {
    "id": "DD6",
    "name": "Shapeshifting",
    "faction": "Druid",
    "tier": 2,
    "cost": "5e26",
    "effect": "Increase Mana Regeneration additively based on assistants owned.",
    "formula": "+(3 * x^0.4), where x = assistants owned",
    "effects": [
      "Mana Regeneration"
    ],
    "scaling": [
      "Assistants Owned"
    ],
    "window": [
      "Era"
    ]
  },
  {
    "id": "DD7",
    "name": "Mabinogion",
    "faction": "Druid",
    "tier": 3,
    "cost": "5e28",
    "effect": "Increase production of all buildings based on their tier, giving the best bonus to the lowest.",
    "formula": "(16 * 2^(12-T))%, where T = building tier",
    "effects": [
      "All Buildings"
    ],
    "scaling": [],
    "window": []
  },
  {
    "id": "DD8",
    "name": "Earthly Soul",
    "faction": "Druid",
    "tier": 3,
    "cost": "5e29",
    "effect": "Increase Mana Regeneration additively based on highest Stone Pillars built this Reincarnation.",
    "formula": "+(1.35 * x^0.35), where x = highest Stone Pillars this Reincarnation",
    "effects": [
      "Mana Regeneration"
    ],
    "scaling": [
      "Specific Building Count"
    ],
    "window": [
      "Reincarnation"
    ]
  },
  {
    "id": "DD9",
    "name": "Building Jungle",
    "faction": "Druid",
    "tier": 3,
    "cost": "5e30",
    "effect": "Increase production of each building based on their quantity.",
    "formula": "(3 * x^0.9)%, where x = buildings of same type owned",
    "effects": [
      "All Buildings"
    ],
    "scaling": [
      "Buildings Owned"
    ],
    "window": [
      "Era"
    ]
  },
  {
    "id": "DD10",
    "name": "Building Vines",
    "faction": "Druid",
    "tier": 4,
    "cost": "1e60",
    "effect": "Increase spell duration based on highest Ziggurats built this Reincarnation.",
    "formula": "(x^0.5)%, where x = highest Ziggurats this Reincarnation",
    "effects": [
      "Spell Duration"
    ],
    "scaling": [
      "Specific Building Count"
    ],
    "window": [
      "Reincarnation"
    ]
  },
  {
    "id": "DD11",
    "name": "Lunar Cycle",
    "faction": "Druid",
    "tier": 4,
    "cost": "1e80",
    "effect": "Increase Maximum Mana additively by online time this Era; multiplicatively by offline time this Era.",
    "formula": "Additive: +(50 * x^0.85) online; Mult: (0.5 * y^0.5)% offline; x/y = online/offline time this Era",
    "effects": [
      "Max Mana"
    ],
    "scaling": [
      "Time Played",
      "Offline Time"
    ],
    "window": [
      "Era",
      "Era"
    ]
  },
  {
    "id": "DD12",
    "name": "Grove Farming",
    "faction": "Druid",
    "tier": 4,
    "cost": "1e95",
    "effect": "Increase production of all buildings based on their tier; middle tiers get best bonus.",
    "formula": "(0.8 * ((6-abs(6-T))^4))%, where T = building tier",
    "effects": [
      "All Buildings"
    ],
    "scaling": [],
    "window": []
  }
]